{
  "results": [
    {
      "id": "213ca18e-1e9a-4f26-8ae6-52280242ef14",
      "recordings": [
        {
          "artists": [
            {
              "id": "596ffa74-3d08-44ef-b113-765d43d12738",
              "name": "Justin Timberlake"
            }
          ],
          "duration": 482,
          "id": "f10ce3b4-d079-471a-9d0d-0cd0a1ff018b",
          "releasegroups": [
            {
              "artists": [
                {
                  "id": "596ffa74-3d08-44ef-b113-765d43d12738",
                  "name": "Justin Timberlake"
                }
              ],
              "id": "deae6fc2-a675-4f35-9565-d2aaea4872c7",
              "title": "The 20/20 Experience",
              "type": "Album"
            },
            {
              "id": "fe51b20f-83e4-49dd-9a36-b8d4da138325",
              "secondarytypes": [
                "Compilation"
              ],
              "title": "The Complete 20/20 Experience",
              "type": "Album"
            }
          ],
          "title": "Pusher Love Girl"
        }
      ],
      "score": 0.947191
    }
  ],
  "status": "ok"
}